fineas/__init__.py
fineas/finite_state_machine.py
fineas-1.0.1.dist-info/LICENSE
fineas-1.0.1.dist-info/WHEEL
fineas-1.0.1.dist-info/METADATA
fineas-1.0.1.dist-info/RECORD
