Metadata-Version: 2.1
Name: fineas
Version: 1.0.1
Summary: A simple, decorator-based, transition-focused Finite State Machine implementation.
License: Apache 2
Author: Chris Blades
Requires-Python: >=3.6.2,<4.0.0
Classifier: License :: Other/Proprietary License
Classifier: Programming Language :: Python :: 3
Classifier: Programming Language :: Python :: 3.10
Classifier: Programming Language :: Python :: 3.7
Classifier: Programming Language :: Python :: 3.8
Classifier: Programming Language :: Python :: 3.9
Requires-Dist: wrapt (>=1.14.0,<2.0.0)
